LICENSE-BSD
MANIFEST.in
README.md
requirements.txt
setup.py
rux/__init__.py
rux/cli.py
rux/config.py
rux/daemon.py
rux/exceptions.py
rux/generator.py
rux/libparser.py
rux/logger.py
rux/models.py
rux/parser.py
rux/pdf.py
rux/renderer.py
rux/server.py
rux/utils.py
rux/res/config.toml
rux/res/clr/.git
rux/res/clr/.gitignore
rux/res/clr/Makefile
rux/res/clr/README.md
rux/res/clr/screenshot-1.png
rux/res/clr/screenshot-2.png
rux/res/clr/fonts-for-local/OFLGoudyStMTT-Italic.ttf
rux/res/clr/fonts-for-local/OFLGoudyStMTT.ttf
rux/res/clr/fonts-for-local/SourceSansPro-Regular.otf
rux/res/clr/sass/base.sass
rux/res/clr/sass/iabc.sass
rux/res/clr/sass/layout.sass
rux/res/clr/sass/normalize.sass
rux/res/clr/sass/pdf.sass
rux/res/clr/sass/text.sass
rux/res/clr/sass/windows.sass
rux/res/clr/static/css/hint.min.css
rux/res/clr/static/css/iabc.css
rux/res/clr/static/css/iconmoon.css
rux/res/clr/static/css/layout.css
rux/res/clr/static/css/noise.png
rux/res/clr/static/css/normalize.css
rux/res/clr/static/css/pdf.css
rux/res/clr/static/css/pygments.css
rux/res/clr/static/css/windows.css
rux/res/clr/static/css/fonts/.DS_Store
rux/res/clr/static/css/fonts/icomoon.eot
rux/res/clr/static/css/fonts/icomoon.svg
rux/res/clr/static/css/fonts/icomoon.ttf
rux/res/clr/static/css/fonts/icomoon.woff
rux/res/clr/static/fonts/OFLGoudyStMTT-Italic.eot
rux/res/clr/static/fonts/OFLGoudyStMTT-Italic.svg
rux/res/clr/static/fonts/OFLGoudyStMTT-Italic.ttf
rux/res/clr/static/fonts/OFLGoudyStMTT-Italic.woff
rux/res/clr/static/fonts/OFLGoudyStMTT.svg
rux/res/clr/static/fonts/OFLGoudyStMTT.ttf
rux/res/clr/static/fonts/OFLGoudyStMTT.woff
rux/res/clr/static/fonts/iABC-Regular.eot
rux/res/clr/static/fonts/iABC-Regular.svg
rux/res/clr/static/fonts/iABC-Regular.woff
rux/res/clr/static/fonts/iABC-SC-Regular.eot
rux/res/clr/static/fonts/iABC-SC-Regular.svg
rux/res/clr/static/fonts/iABC-SC-Regular.woff
rux/res/clr/static/fonts/windows/iABC-SC-Regular.eot
rux/res/clr/static/fonts/windows/iABC-SC-Regular.svg
