Metadata-Version: 1.1
Name: rux
Version: 0.6.6
Summary: Micro & Fast static blog generator based on markdown
Home-page: http://github.com/hit9/rux
Author: hit9
Author-email: nz2324@126.com
License: BSD
Keywords: static blog generator markdown,html
Platform: UNKNOWN
Classifier: Development Status :: 4 - Beta
Classifier: Environment :: Console
Classifier: Intended Audience :: Customer Service
Classifier: License :: OSI Approved :: BSD License
Classifier: Operating System :: POSIX
Classifier: Programming Language :: Python
